{
  "generated": "2026-06-29 22:10 UTC",
  "method": "Boot/nation: Binomial player-share model over the 100k simulated tournaments; shares from international goals 2024-26. Glove: heuristic rank (reach-final prob x defensive record). Ball: Polymarket prices only.",
  "golden_boot": [
    {
      "player": "H. Kane",
      "team": "England",
      "intl_goals_24_26": 19,
      "exp_goals": 3.82,
      "p_model": 0.2043,
      "market": 0.125,
      "edge": 0.0793
    },
    {
      "player": "J. David",
      "team": "Canada",
      "intl_goals_24_26": 11,
      "exp_goals": 3.08,
      "p_model": 0.0988,
      "market": null,
      "edge": null
    },
    {
      "player": "Mikel Oyarzabal",
      "team": "Spain",
      "intl_goals_24_26": 17,
      "exp_goals": 2.73,
      "p_model": 0.0782,
      "market": 0.075,
      "edge": 0.0032
    },
    {
      "player": "Kylian Mbappé",
      "team": "France",
      "intl_goals_24_26": 10,
      "exp_goals": 2.62,
      "p_model": 0.0702,
      "market": 0.145,
      "edge": -0.0748
    },
    {
      "player": "Lautaro Martínez",
      "team": "Argentina",
      "intl_goals_24_26": 16,
      "exp_goals": 2.61,
      "p_model": 0.065,
      "market": 0.0225,
      "edge": 0.0425
    },
    {
      "player": "E. Haaland",
      "team": "Norway",
      "intl_goals_24_26": 30,
      "exp_goals": 2.29,
      "p_model": 0.0513,
      "market": 0.055,
      "edge": -0.0037
    },
    {
      "player": "Cristiano Ronaldo",
      "team": "Portugal",
      "intl_goals_24_26": 15,
      "exp_goals": 2.09,
      "p_model": 0.0387,
      "market": 0.0435,
      "edge": -0.0048
    },
    {
      "player": "R. Jiménez",
      "team": "Mexico",
      "intl_goals_24_26": 10,
      "exp_goals": 2.13,
      "p_model": 0.0314,
      "market": null,
      "edge": null
    },
    {
      "player": "L. Messi",
      "team": "Argentina",
      "intl_goals_24_26": 13,
      "exp_goals": 2.12,
      "p_model": 0.0298,
      "market": 0.0415,
      "edge": -0.0117
    },
    {
      "player": "Brahim Díaz",
      "team": "Morocco",
      "intl_goals_24_26": 13,
      "exp_goals": 1.87,
      "p_model": 0.0224,
      "market": 0.0125,
      "edge": 0.0099
    },
    {
      "player": "F. Wirtz",
      "team": "Germany",
      "intl_goals_24_26": 11,
      "exp_goals": 1.78,
      "p_model": 0.0184,
      "market": null,
      "edge": null
    },
    {
      "player": "M. Olise",
      "team": "France",
      "intl_goals_24_26": 7,
      "exp_goals": 1.83,
      "p_model": 0.0181,
      "market": 0.048,
      "edge": -0.0299
    },
    {
      "player": "B. Embolo",
      "team": "Switzerland",
      "intl_goals_24_26": 11,
      "exp_goals": 1.81,
      "p_model": 0.0164,
      "market": null,
      "edge": null
    },
    {
      "player": "V. Gyökeres",
      "team": "Sweden",
      "intl_goals_24_26": 21,
      "exp_goals": 1.49,
      "p_model": 0.0122,
      "market": 0.0075,
      "edge": 0.0047
    },
    {
      "player": "L. Díaz",
      "team": "Colombia",
      "intl_goals_24_26": 13,
      "exp_goals": 1.44,
      "p_model": 0.0118,
      "market": 0.0125,
      "edge": -0.0007
    },
    {
      "player": "S. Mané",
      "team": "Senegal",
      "intl_goals_24_26": 9,
      "exp_goals": 1.48,
      "p_model": 0.0114,
      "market": 0.003,
      "edge": 0.0084
    },
    {
      "player": "Vinícius Júnior",
      "team": "Brazil",
      "intl_goals_24_26": 6,
      "exp_goals": 1.57,
      "p_model": 0.0113,
      "market": 0.027,
      "edge": -0.0157
    },
    {
      "player": "Raphinha",
      "team": "Brazil",
      "intl_goals_24_26": 6,
      "exp_goals": 1.56,
      "p_model": 0.0109,
      "market": 0.0345,
      "edge": -0.0236
    },
    {
      "player": "Son Heung-Min",
      "team": "South Korea",
      "intl_goals_24_26": 12,
      "exp_goals": 1.45,
      "p_model": 0.0094,
      "market": null,
      "edge": null
    },
    {
      "player": "K. De Bruyne",
      "team": "Belgium",
      "intl_goals_24_26": 11,
      "exp_goals": 1.48,
      "p_model": 0.0092,
      "market": null,
      "edge": null
    },
    {
      "player": "C. Gakpo",
      "team": "Netherlands",
      "intl_goals_24_26": 12,
      "exp_goals": 1.36,
      "p_model": 0.008,
      "market": 0.022,
      "edge": -0.014
    },
    {
      "player": "Bruno Fernandes",
      "team": "Portugal",
      "intl_goals_24_26": 10,
      "exp_goals": 1.4,
      "p_model": 0.0078,
      "market": 0.0095,
      "edge": -0.0017
    },
    {
      "player": "S. Rahimi",
      "team": "Morocco",
      "intl_goals_24_26": 10,
      "exp_goals": 1.43,
      "p_model": 0.0077,
      "market": null,
      "edge": null
    },
    {
      "player": "M. Taremi",
      "team": "Iran",
      "intl_goals_24_26": 7,
      "exp_goals": 1.34,
      "p_model": 0.0077,
      "market": null,
      "edge": null
    },
    {
      "player": "A. Ueda",
      "team": "Japan",
      "intl_goals_24_26": 10,
      "exp_goals": 1.34,
      "p_model": 0.0076,
      "market": null,
      "edge": null
    }
  ],
  "top_scorer_nation": [
    {
      "team": "Spain",
      "exp_goals": 11.99,
      "p_model": 0.1796,
      "market": 0.205,
      "edge": -0.0254
    },
    {
      "team": "Argentina",
      "exp_goals": 11.61,
      "p_model": 0.155,
      "market": 0.0665,
      "edge": 0.0885
    },
    {
      "team": "Brazil",
      "exp_goals": 11.03,
      "p_model": 0.1188,
      "market": 0.095,
      "edge": 0.0238
    },
    {
      "team": "England",
      "exp_goals": 10.5,
      "p_model": 0.0937,
      "market": 0.125,
      "edge": -0.0313
    },
    {
      "team": "France",
      "exp_goals": 9.63,
      "p_model": 0.0764,
      "market": 0.165,
      "edge": -0.0886
    },
    {
      "team": "Germany",
      "exp_goals": 9.3,
      "p_model": 0.0559,
      "market": 0.115,
      "edge": -0.0591
    },
    {
      "team": "Portugal",
      "exp_goals": 8.7,
      "p_model": 0.0535,
      "market": 0.0555,
      "edge": -0.002
    },
    {
      "team": "Belgium",
      "exp_goals": 8.82,
      "p_model": 0.0436,
      "market": 0.0405,
      "edge": 0.0031
    },
    {
      "team": "Canada",
      "exp_goals": 9.62,
      "p_model": 0.0404,
      "market": 0.004,
      "edge": 0.0364
    },
    {
      "team": "United States",
      "exp_goals": 7.97,
      "p_model": 0.0328,
      "market": 0.009,
      "edge": 0.0238
    },
    {
      "team": "Netherlands",
      "exp_goals": 7.28,
      "p_model": 0.0236,
      "market": 0.032,
      "edge": -0.0084
    },
    {
      "team": "Switzerland",
      "exp_goals": 8.21,
      "p_model": 0.0185,
      "market": 0.0135,
      "edge": 0.005
    },
    {
      "team": "Japan",
      "exp_goals": 6.83,
      "p_model": 0.0172,
      "market": 0.0075,
      "edge": 0.0097
    },
    {
      "team": "Morocco",
      "exp_goals": 7.19,
      "p_model": 0.0152,
      "market": 0.0035,
      "edge": 0.0117
    },
    {
      "team": "Colombia",
      "exp_goals": 6.52,
      "p_model": 0.0152,
      "market": 0.0105,
      "edge": 0.0047
    }
  ],
  "golden_glove": [
    {
      "player": "E. Martínez",
      "team": "Argentina",
      "score": 0.358,
      "p_final": 0.2868,
      "conceded_pg": 0.3,
      "market": 0.19
    },
    {
      "player": "Unai Simón",
      "team": "Spain",
      "score": 0.27,
      "p_final": 0.2434,
      "conceded_pg": 0.4,
      "market": 0.125
    },
    {
      "player": "J. Pickford",
      "team": "England",
      "score": 0.182,
      "p_final": 0.1822,
      "conceded_pg": 0.5,
      "market": 0.16
    },
    {
      "player": "Y. Bounou",
      "team": "Morocco",
      "score": 0.127,
      "p_final": 0.1015,
      "conceded_pg": 0.3,
      "market": 0.03
    },
    {
      "player": "M. Maignan",
      "team": "France",
      "score": 0.111,
      "p_final": 0.1558,
      "conceded_pg": 0.9,
      "market": 0.145
    },
    {
      "player": "Alisson Becker",
      "team": "Brazil",
      "score": 0.111,
      "p_final": 0.1778,
      "conceded_pg": 1.1,
      "market": 0.165
    },
    {
      "player": "Diogo Costa",
      "team": "Portugal",
      "score": 0.085,
      "p_final": 0.1281,
      "conceded_pg": 1.0,
      "market": 0.145
    },
    {
      "player": "T. Courtois",
      "team": "Belgium",
      "score": 0.064,
      "p_final": 0.0706,
      "conceded_pg": 0.6,
      "market": 0.08
    },
    {
      "player": "T. Hayakawa",
      "team": "Japan",
      "score": 0.059,
      "p_final": 0.0647,
      "conceded_pg": 0.6,
      "market": null
    },
    {
      "player": "O. Baumann",
      "team": "Germany",
      "score": 0.053,
      "p_final": 0.0692,
      "conceded_pg": 0.8,
      "market": 0.0245
    },
    {
      "player": "C. Vargas",
      "team": "Colombia",
      "score": 0.046,
      "p_final": 0.0693,
      "conceded_pg": 1.0,
      "market": null
    },
    {
      "player": "B. Verbruggen",
      "team": "Netherlands",
      "score": 0.044,
      "p_final": 0.0571,
      "conceded_pg": 0.8,
      "market": 0.125
    },
    {
      "player": "H. Galíndez",
      "team": "Ecuador",
      "score": 0.038,
      "p_final": 0.0384,
      "conceded_pg": 0.5,
      "market": null
    },
    {
      "player": "S. Rochet",
      "team": "Uruguay",
      "score": 0.033,
      "p_final": 0.0467,
      "conceded_pg": 0.9,
      "market": 0.06
    },
    {
      "player": "D. St. Clair",
      "team": "Canada",
      "score": 0.031,
      "p_final": 0.0276,
      "conceded_pg": 0.4,
      "market": null
    }
  ],
  "golden_ball": [
    {
      "player": "Lamine Yamal",
      "market": 0.115,
      "team": "Spain",
      "team_champion_p": 0.1408
    },
    {
      "player": "Kylian Mbappé",
      "market": 0.095,
      "team": "France",
      "team_champion_p": 0.0817
    },
    {
      "player": "Michael Olise",
      "market": 0.08,
      "team": "France",
      "team_champion_p": 0.0817
    },
    {
      "player": "Harry Kane",
      "market": 0.07,
      "team": "England",
      "team_champion_p": 0.104
    },
    {
      "player": "Lionel Messi",
      "market": 0.07,
      "team": "Argentina",
      "team_champion_p": 0.1896
    },
    {
      "player": "Bruno Fernandes",
      "market": 0.065,
      "team": "Portugal",
      "team_champion_p": 0.0662
    },
    {
      "player": "Pedri",
      "market": 0.06,
      "team": "Spain",
      "team_champion_p": 0.1408
    },
    {
      "player": "Vinícius Jr.",
      "market": 0.0375,
      "team": null,
      "team_champion_p": null
    },
    {
      "player": "Vitinha",
      "market": 0.0375,
      "team": "Portugal",
      "team_champion_p": 0.0662
    },
    {
      "player": "Ousmane Dembélé",
      "market": 0.033,
      "team": "France",
      "team_champion_p": 0.0817
    },
    {
      "player": "Florian Wirtz",
      "market": 0.033,
      "team": "Germany",
      "team_champion_p": 0.0286
    },
    {
      "player": "Cristiano Ronaldo",
      "market": 0.0325,
      "team": "Portugal",
      "team_champion_p": 0.0662
    },
    {
      "player": "Rayan Cherki",
      "market": 0.0265,
      "team": "France",
      "team_champion_p": 0.0817
    },
    {
      "player": "Erling Haaland",
      "market": 0.026,
      "team": "Norway",
      "team_champion_p": 0.0103
    },
    {
      "player": "Jude Bellingham",
      "market": 0.0255,
      "team": "England",
      "team_champion_p": 0.104
    }
  ],
  "prices_at": "2026-06-10 14:54 UTC"
}